analysis/cpw/src/plot_cpw_from_cache.py
analysis/cpw/src/process_results.py
analysis/impact_of_voxelization/voxelization.py
analysis/screenshot_analysis/analyze_screenshots.py
analysis/screenshot_analysis/get_screenshot.py
analysis/screenshot_analysis/plot_results.py
analysis/sensitivity_analysis/__init__.py
analysis/sensitivity_analysis/gui.py
analysis/sensitivity_analysis/run_sensitivity_analysis.py
analysis/timing_analysis/create_heatmap.py
analysis/timing_analysis/log_parser.py
analysis/timing_analysis/parse_timing_log.py
cli/__init__.py
cli/__main__.py
cli/ascii_art.py
cli/commands.py
cli/generate_paper.py
cli/run_ai.py
cli/run_analysis.py
cli/run_free_space_study.py
cli/run_parallel_studies.py
cli/run_study.py
cli/run_super_study.py
cli/run_worker.py
cli/utils.py
goliat/__init__.py
goliat/antenna.py
goliat/colors.py
goliat/constants.py
goliat/data_extractor.py
goliat/gui_manager.py
goliat/logging_manager.py
goliat/metadata_exporter.py
goliat/profiler.py
goliat/project_manager.py
goliat/results_extractor.py
goliat/simulation_runner.py
goliat/ai/__init__.py
goliat/ai/assistant.py
goliat/ai/chat_handler.py
goliat/ai/config.py
goliat/ai/cost_tracker.py
goliat/ai/embedding_indexer.py
goliat/ai/error_advisor.py
goliat/ai/query_processor.py
goliat/ai/types.py
goliat/analysis/__init__.py
goliat/analysis/analyze_simulation_stats.py
goliat/analysis/analyzer.py
goliat/analysis/base_strategy.py
goliat/analysis/compare.py
goliat/analysis/create_excel_for_partners.py
goliat/analysis/far_field_strategy.py
goliat/analysis/near_field_strategy.py
goliat/analysis/parallel_plot_executor.py
goliat/analysis/parse_verbose_log.py
goliat/analysis/plotter.py
goliat/analysis/plots/__init__.py
goliat/analysis/plots/bar.py
goliat/analysis/plots/base.py
goliat/analysis/plots/boxplot.py
goliat/analysis/plots/bubble.py
goliat/analysis/plots/cdf.py
goliat/analysis/plots/correlation.py
goliat/analysis/plots/heatmap.py
goliat/analysis/plots/line.py
goliat/analysis/plots/outliers.py
goliat-1.4.0.dist-info/licenses/LICENSE
goliat-1.4.0.dist-info/METADATA
goliat-1.4.0.dist-info/WHEEL
goliat-1.4.0.dist-info/entry_points.txt
goliat-1.4.0.dist-info/top_level.txt
goliat-1.4.0.dist-info/RECORD
