Metadata-Version: 2.4
Name: goliat
Version: 1.4.0
Summary: A Python framework for dosimetric assessments using Sim4Life.
Author-email: rwydaegh <robin.wydaeghe@ugent.be>
License: Apache-2.0
Project-URL: Documentation, https://rwydaegh.github.io/goliat/
Project-URL: Homepage, https://rwydaegh.github.io/goliat/
Project-URL: Issues, https://github.com/rwydaegh/goliat/issues
Project-URL: Repository, https://github.com/rwydaegh/goliat
Keywords: emf,dosimetry,sar,sim4life,electromagnetic,simulation,near-field,far-field,phantom,antenna
Classifier: Development Status :: 4 - Beta
Classifier: Intended Audience :: Science/Research
Classifier: Topic :: Scientific/Engineering :: Physics
Classifier: Topic :: Scientific/Engineering :: Medical Science Apps.
Classifier: License :: OSI Approved :: Apache Software License
Classifier: Programming Language :: Python :: 3
Classifier: Programming Language :: Python :: 3.8
Classifier: Programming Language :: Python :: 3.9
Classifier: Programming Language :: Python :: 3.10
Classifier: Programming Language :: Python :: 3.11
Classifier: Operating System :: Microsoft :: Windows
Classifier: Operating System :: POSIX :: Linux
Requires-Python: >=3.8
License-File: LICENSE
Requires-Dist: numpy<2
Requires-Dist: pandas
Requires-Dist: scipy
Requires-Dist: gdown
Requires-Dist: seaborn
Requires-Dist: matplotlib
Requires-Dist: line-profiler
Requires-Dist: pytest
Requires-Dist: scienceplots
Requires-Dist: PySide6
Requires-Dist: osparc
Requires-Dist: colorama
Requires-Dist: python-dotenv
Requires-Dist: psutil
Requires-Dist: h5py
Requires-Dist: requests
Requires-Dist: openpyxl
Requires-Dist: pywin32; sys_platform == "win32"
Provides-Extra: ai
Requires-Dist: openai>=1.0.0; extra == "ai"
Requires-Dist: rich>=13.0.0; extra == "ai"
Provides-Extra: docs
Requires-Dist: mkdocs; extra == "docs"
Requires-Dist: mkdocs-material==9.5.3; extra == "docs"
Requires-Dist: pymdown-extensions==10.7; extra == "docs"
Requires-Dist: mkdocstrings[python]; extra == "docs"
Requires-Dist: mkdocs-mermaid2-plugin; extra == "docs"
Requires-Dist: mkdocs-panzoom-plugin; extra == "docs"
Requires-Dist: mkdocs-git-revision-date-localized-plugin; extra == "docs"
Requires-Dist: mkdocs-minify-plugin; extra == "docs"
Requires-Dist: mkdocs-kroki-plugin; extra == "docs"
Requires-Dist: mknotebooks>=0.8.0; extra == "docs"
Requires-Dist: ansi2html>=1.8.0; extra == "docs"
Dynamic: license-file
